smb_path/__about__.py
smb_path/__init__.py
smb_path/_version.py
smb_path/path_patch.py
smb_path/smb_path.py
smb_path.pth
smb_path-0.6.2.dist-info/METADATA
smb_path-0.6.2.dist-info/WHEEL
smb_path-0.6.2.dist-info/licenses/LICENSE
smb_path-0.6.2.dist-info/RECORD
