Metadata-Version: 2.4
Name: smb-path
Version: 0.6.2
Summary: pathlib-like Path object for smb protocol
Project-URL: Changelog, https://github.com/m-birke/smb-path/blob/main/CHANGELOG.md
Project-URL: Documentation, https://github.com/m-birke/smb-path#readme
Project-URL: Homepage, https://github.com/m-birke/smb-path
Project-URL: Issues, https://github.com/m-birke/smb-path/issues
Project-URL: Source, https://github.com/m-birke/smb-path
Author-email: m-birke <wesci@web.de>
License-Expression: MIT
License-File: LICENSE
Keywords: Fileshare,Path,SMB,SMBv2,SMBv3,pathlib
Classifier: Development Status :: 4 - Beta
Classifier: License :: OSI Approved :: MIT License
Classifier: Operating System :: Microsoft :: Windows
Classifier: Operating System :: POSIX :: Linux
Classifier: Programming Language :: Python
Classifier: Programming Language :: Python :: 3.8
Classifier: Programming Language :: Python :: 3.9
Classifier: Programming Language :: Python :: 3.10
Classifier: Programming Language :: Python :: 3.11
Classifier: Programming Language :: Python :: 3.12
Classifier: Programming Language :: Python :: 3.13
Classifier: Programming Language :: Python :: Implementation :: CPython
Classifier: Typing :: Typed
Requires-Python: >=3.8
Requires-Dist: smbprotocol
Requires-Dist: wrapt
